vcode/__init__.py
vcode/vcode.py
vcode-0.0.2.dist-info/LICENSE
vcode-0.0.2.dist-info/METADATA
vcode-0.0.2.dist-info/WHEEL
vcode-0.0.2.dist-info/top_level.txt
vcode-0.0.2.dist-info/RECORD
